pyproject.toml
efinance/__init__.py
efinance/api/__init__.py
efinance/bond/__init__.py
efinance/bond/config.py
efinance/bond/getter.py
efinance/common/__init__.py
efinance/common/config.py
efinance/common/getter.py
efinance/config/__init__.py
efinance/fund/__init__.py
efinance/fund/config.py
efinance/fund/getter.py
efinance/fund/utils.py
efinance/futures/__init__.py
efinance/futures/config.py
efinance/futures/getter.py
efinance/futures/utils.py
efinance/shared/__init__.py
efinance/stock/__init__.py
efinance/stock/config.py
efinance/stock/getter.py
efinance/stock/utils.py
efinance/utils/__init__.py
efinance-0.5.5.1.dist-info/LICENSE
efinance-0.5.5.1.dist-info/METADATA
efinance-0.5.5.1.dist-info/WHEEL
efinance-0.5.5.1.dist-info/top_level.txt
efinance-0.5.5.1.dist-info/RECORD
