Metadata-Version: 2.2
Name: efinance
Version: 0.5.5.1
Summary: A finance tool to get stock,fund and futures data base on eastmoney
Author-email: micro sheep <micro-sheep@outlook.com>
License: MIT
Project-URL: Homepage, https://github.com/Micro-sheep/efinance
Project-URL: Documentation, https://efinance.readthedocs.io
Project-URL: Source, https://github.com/Micro-sheep/efinance
Keywords: finance,quant,stock,fund,futures
Classifier: License :: OSI Approved :: MIT License
Classifier: Programming Language :: Python :: 3.6
Classifier: Programming Language :: Python :: 3.7
Classifier: Programming Language :: Python :: 3.8
Classifier: Programming Language :: Python :: 3.9
Classifier: Programming Language :: Python :: 3.10
Classifier: Programming Language :: Python :: 3.11
Classifier: Programming Language :: Python :: 3.12
License-File: LICENSE
Requires-Dist: requests
Requires-Dist: tqdm
Requires-Dist: pandas
Requires-Dist: retry
Requires-Dist: multitasking
Requires-Dist: jsonpath
Requires-Dist: rich
Requires-Dist: beautifulsoup4
Requires-Dist: tomli
